pytest_failed_to_verify.py
pytest_failed_to_verify-0.1.5.dist-info/LICENSE
pytest_failed_to_verify-0.1.5.dist-info/METADATA
pytest_failed_to_verify-0.1.5.dist-info/WHEEL
pytest_failed_to_verify-0.1.5.dist-info/entry_points.txt
pytest_failed_to_verify-0.1.5.dist-info/top_level.txt
pytest_failed_to_verify-0.1.5.dist-info/RECORD
