Metadata-Version: 2.1
Name: pytest-failed-to-verify
Version: 0.1.5
Summary: A pytest plugin that helps better distinguishing real test failures from setup flakiness.
Home-page: https://github.com/gastrofix-gmbh/pytest-failed-to-verify
Author: Gastrofix GmbH
Author-email: tech@gastrofix.com
Maintainer: Gastrofix GmbH
Maintainer-email: tech@gastrofix.com
License: MPL
Platform: UNKNOWN
Classifier: Development Status :: 5 - Production/Stable
Classifier: Framework :: Pytest
Classifier: Intended Audience :: Developers
Classifier: Topic :: Software Development :: Testing
Classifier: Programming Language :: Python
Classifier: Programming Language :: Python :: 2
Classifier: Programming Language :: Python :: 2.7
Classifier: Programming Language :: Python :: 3
Classifier: Programming Language :: Python :: 3.4
Classifier: Programming Language :: Python :: 3.5
Classifier: Programming Language :: Python :: 3.6
Classifier: Programming Language :: Python :: 3.7
Classifier: Programming Language :: Python :: Implementation :: CPython
Classifier: Programming Language :: Python :: Implementation :: PyPy
Classifier: Operating System :: OS Independent
Classifier: License :: OSI Approved :: Mozilla Public License 2.0 (MPL 2.0)
Requires-Python: >=2.7, !=3.0.*, !=3.1.*, !=3.2.*, !=3.3.*
Requires-Dist: pytest (>=4.1.0)
